search_fusion/__init__.py
search_fusion/fusion.py
search_fusion/spice.py
search_fusion-0.1.dist-info/METADATA
search_fusion-0.1.dist-info/WHEEL
search_fusion-0.1.dist-info/top_level.txt
search_fusion-0.1.dist-info/RECORD
