Metadata-Version: 2.1
Name: search-fusion
Version: 0.1
Requires-Dist: ollama >=0.2.1
Requires-Dist: requests >=2.32.3
Requires-Dist: tqdm >=4.66.4
Requires-Dist: faiss-cpu >=1.8.0
Requires-Dist: numpy >=1.26.4
